{
  "rulesDirectory": "node_modules/tslint-eslint-rules/dist/rules",
  "extends": "tslint:latest",
  "rules": {
    "indent": [true,
      "spaces"
    ],
    "quotemark": [true,
      "single",
      "avoid-escape"
    ],
    "max-line-length": [true, 100],
    "no-consecutive-blank-lines": [true, 2],
    "only-arrow-functions": false,
    "no-console": [false],
    "object-literal-sort-keys": false,
    "object-literal-shorthand": false,
    "arrow-parens": false,
    "trailing-comma": false,
    "ter-indent": [true, 2],
    "no-unused-expression": false,
    "object-curly-spacing": [
      true,
      "always"
    ]
  }
}
